{
  "season_id": 45,
  "tournament_date": "2026-05-27",
  "players": [
    {
      "Firstname": "J",
      "Lastname": "J",
      "NbTournaments": 1,
      "NthBest": 0,
      "TotalMatchPoints": 9,
      "AveragePointsByTournament": 9.0,
      "Trophies": [
        {
          "Count": 1,
          "Name": "DSK Champion",
          "Css": "ss ss-dft ss-mythic"
        },
        {
          "Count": 1,
          "Name": "FF Draft Winner",
          "Css": "fa fa-trophy ss-uncommon"
        },
        {
          "Count": 1,
          "Name": "FIN Champion",
          "Css": "ss ss-fin ss-mythic"
        },
        {
          "Count": 1,
          "Name": "Qualified for Magic Mates Monday Cup 2026",
          "Css": "fa fa-check ss-rare"
        },
        {
          "Count": 2,
          "Name": "Cube",
          "Css": "fa fa-star ss-uncommon"
        },
        {
          "Count": 1,
          "Name": "Draft Trophy TLA",
          "Css": "fa fa-trophy ss-uncommon"
        },
        {
          "Count": 1,
          "Name": "Draft Trophy ECL",
          "Css": "fa fa-trophy ss-uncommon"
        }
      ]
    },
    {
      "Firstname": "Brandon",
      "Lastname": "Smith",
      "NbTournaments": 1,
      "NthBest": 0,
      "TotalMatchPoints": 6,
      "AveragePointsByTournament": 6.0,
      "Trophies": []
    },
    {
      "Firstname": "Dylan",
      "Lastname": "Tevardy-O'Neil",
      "NbTournaments": 1,
      "NthBest": 0,
      "TotalMatchPoints": 6,
      "AveragePointsByTournament": 6.0,
      "Trophies": [
        {
          "Count": 1,
          "Name": "Draft Trophy TDM",
          "Css": "fa fa-trophy ss-uncommon"
        },
        {
          "Count": 1,
          "Name": "Draft Trophy ECL",
          "Css": "fa fa-trophy ss-uncommon"
        }
      ]
    },
    {
      "Firstname": "Robert",
      "Lastname": "McDougall",
      "NbTournaments": 1,
      "NthBest": 0,
      "TotalMatchPoints": 6,
      "AveragePointsByTournament": 6.0,
      "Trophies": [
        {
          "Count": 1,
          "Name": "Draft Trophy TLA",
          "Css": "fa fa-trophy ss-uncommon"
        },
        {
          "Count": 1,
          "Name": "Draft Trophy ECL",
          "Css": "fa fa-trophy ss-uncommon"
        }
      ]
    },
    {
      "Firstname": "Sebastian",
      "Lastname": "Restrepo",
      "NbTournaments": 1,
      "NthBest": 0,
      "TotalMatchPoints": 3,
      "AveragePointsByTournament": 3.0,
      "Trophies": []
    },
    {
      "Firstname": "Matt",
      "Lastname": "Sellas",
      "NbTournaments": 1,
      "NthBest": 0,
      "TotalMatchPoints": 3,
      "AveragePointsByTournament": 3.0,
      "Trophies": []
    },
    {
      "Firstname": "Dom",
      "Lastname": "Smith-Devine",
      "NbTournaments": 1,
      "NthBest": 0,
      "TotalMatchPoints": 3,
      "AveragePointsByTournament": 3.0,
      "Trophies": [
        {
          "Count": 1,
          "Name": "Cube",
          "Css": "fa fa-star ss-uncommon"
        },
        {
          "Count": 1,
          "Name": "Draft Trophy TLA",
          "Css": "fa fa-trophy ss-uncommon"
        }
      ]
    }
  ]
}